lbCta/__init__.py
lbCta/cta.py
lbCta/scripts/__init__.py
lbCta/scripts/query.py
lbCta/scripts/recall.py
lbCta/scripts/status.py
lbcta-1.1.17.dist-info/licenses/LICENSE
lbcta-1.1.17.dist-info/METADATA
lbcta-1.1.17.dist-info/WHEEL
lbcta-1.1.17.dist-info/entry_points.txt
lbcta-1.1.17.dist-info/top_level.txt
lbcta-1.1.17.dist-info/RECORD
