Metadata-Version: 2.4
Name: lbCta
Version: 1.1.17
Summary: LHCb interface to EOS/CTA package
Home-page: https://gitlab.cern.ch/lhcb-online/lhcb-online-cta
Author: LHCb Online team
Author-email: lbonsupp@cern.ch
License: GNU General Public License v3
Keywords: LHCb
Classifier: Development Status :: 4 - Beta
Classifier: Environment :: Console
Classifier: Operating System :: POSIX :: Linux
Classifier: License :: OSI Approved :: GNU General Public License v3 (GPLv3)
Classifier: Programming Language :: Python :: 3
Requires-Python: >=3.9
License-File: LICENSE
Requires-Dist: setuptools
Provides-Extra: testing
Requires-Dist: black; extra == "testing"
Requires-Dist: pylint; extra == "testing"
Requires-Dist: pytest>=6.0; extra == "testing"
Dynamic: license-file
